[{"model": "images.image", "pk": 9, "fields": {"user": 11, "title": "How to learn english", "slug": "how-to-learn-english", "url": "https://charbzaban.com/wp-content/uploads/2018/06/12-960x640.jpg", "image": "images/2021/06/21/how-to-learn-english.jpg", "description": "there are bunch of ways to learn English, so you have to keep in mind that you must work fucking hard to learn to do it.", "created": "2021-06-21T12:20:21.351Z", "likes": [5, 6]}}, {"model": "images.image", "pk": 10, "fields": {"user": 10, "title": "How to make decision", "slug": "how-to-make-decision", "url": "https://www.computersciencedegreehub.com/wp-content/uploads/2016/02/what-is-coding-1024x683.jpg", "image": "images/2021/06/21/how-to-make-decision.jpg", "description": "You have to learn to make those investigations in your own life", "created": "2021-06-21T16:32:24.863Z", "likes": []}}, {"model": "images.image", "pk": 11, "fields": {"user": 9, "title": "stay alive", "slug": "stay-alive", "url": "https://static.qobuz.com/images/covers/4b/y8/ikgyr46kjy84b_600.jpg", "image": "images/2021/06/21/stay-alive.jpg", "description": "someone told me to be you own destination, you have to learn to make those investigations in your own life", "created": "2021-06-21T16:34:02.771Z", "likes": []}}, {"model": "images.image", "pk": 12, "fields": {"user": 8, "title": "focus", "slug": "focus", "url": "https://img.freepik.com/free-photo/bodybuilder-showing-his-muscles_136403-5511.jpg", "image": "images/2021/06/21/focus.jpg", "description": "You know how do i feel about yo to become the man of the true life", "created": "2021-06-21T16:37:30.653Z", "likes": []}}, {"model": "images.image", "pk": 14, "fields": {"user": 7, "title": "true man", "slug": "true-man", "url": "https://nypost.com/wp-content/uploads/sites/2/2016/07/buff6.jpg", "image": "images/2021/06/21/true-man.jpg", "description": "Salman barani is that guy who knows a lot to master.", "created": "2021-06-21T16:41:28.965Z", "likes": []}}]